spfifo
