Metadata-Version: 2.1
Name: SPFIFO
Version: 1.2.0
Summary: FIFO share for multiprocess
Home-page: https://github.com/
Author: Nguyen Thanh Son
Author-email: thanhson.rf@gmail.com
License: UNKNOWN
Keywords: fifo multiprocess
Platform: UNKNOWN
Classifier: Programming Language :: Python :: 2
Classifier: Programming Language :: Python :: 2.7
Classifier: Programming Language :: Python :: 3
Classifier: Programming Language :: Python :: 3.4
Classifier: Programming Language :: Python :: 3.5
Classifier: Programming Language :: Python :: 3.6
Classifier: License :: OSI Approved :: MIT License
Classifier: Operating System :: OS Independent
